Consensus/ConfigManager.py
Consensus/EsriConnector.py
Consensus/EsriServers.py
Consensus/GeocodeMerger.py
Consensus/LGInform.py
Consensus/LocalMerger.py
Consensus/Nomis.py
Consensus/__init__.py
Consensus/config_utils.py
Consensus/server_selector_util.py
Consensus/utils.py
Consensus/PickleJar/Open_Geography_Portal.pickle
Consensus/PickleJar/TFL.pickle
Consensus/PickleJar/__init__.py
Consensus/config/__init__.py
Consensus/lookups/Open_Geography_Portal_lookup.json
Consensus/lookups/TFL_lookup.json
Consensus/lookups/__init__.py
consensus-1.2.2.dist-info/licenses/LICENSE
tests/__init__.py
tests/test_ConfigManager.py
tests/test_EsriConnector.py
tests/test_FeatureServer.py
tests/test_GeocodeMerger.py
tests/test_LGInform.py
tests/test_LocalMerger.py
tests/test_Nomis.py
tests/test_OGP.py
tests/test_TFL.py
tests/test_pipeline.py
consensus-1.2.2.dist-info/METADATA
consensus-1.2.2.dist-info/WHEEL
consensus-1.2.2.dist-info/top_level.txt
consensus-1.2.2.dist-info/RECORD
