Metadata-Version: 2.4
Name: Consensus
Version: 1.2.2
Home-page: https://ilkka-lbl.github.io/Consensus/
Author: Ilkka Sipila
Author-email: ilkka.sipila@lewisham.gov.uk
Requires-Python: >=3.9
License-File: LICENSE
Requires-Dist: pandas>=1.5
Requires-Dist: openpyxl>=3.0
Requires-Dist: geopandas>=1.0
Requires-Dist: more-itertools>=10.4
Requires-Dist: numpy>=1.26
Requires-Dist: aiofiles>=24.1
Requires-Dist: aiohttp>=3.10
Requires-Dist: aiosignal>=1.3
Requires-Dist: alabaster>=0.7
Requires-Dist: docutils>=0.18
Requires-Dist: m2r2>=0.3
Requires-Dist: python-dotenv>=1.0
Requires-Dist: PyYAML>=6.0
Requires-Dist: shapely>=2.0
Requires-Dist: Sphinx>=7.3
Requires-Dist: sphinx-autodoc-typehints>=2.3
Requires-Dist: sphinx-rtd-theme>=3.0
Requires-Dist: twine>=5.1
Requires-Dist: pytest>=7.1
Requires-Dist: duckdb>=1.1
Requires-Dist: networkx>=3.2
Dynamic: author
Dynamic: author-email
Dynamic: description
Dynamic: description-content-type
Dynamic: home-page
Dynamic: license-file
Dynamic: requires-dist
Dynamic: requires-python
